PacketHandler/ExampleUsage.py
PacketHandler/Packet.py
PacketHandler/Tests/Test_1.py
PacketHandler/core/DataEnums.py
PacketHandler/core/helpers.py
PacketHandler-1.0.9.2.dist-info/LICENSE.txt
PacketHandler-1.0.9.2.dist-info/METADATA
PacketHandler-1.0.9.2.dist-info/WHEEL
PacketHandler-1.0.9.2.dist-info/top_level.txt
PacketHandler-1.0.9.2.dist-info/RECORD
