Metadata-Version: 2.1
Name: PacketHandler
Version: 1.0.9.2
Summary: Store data as packet. Send, Recv, Encrypt and Compress it. You will be able to manage **socket communication** easily and comprehensibly using this Python package.
Home-page: https://github.com/emrecpp/PacketHandler
Download-URL: https://pypi.org/project/PacketHandler/
Author: Emre Demircan
Author-email: emrecpp1@gmail.com
License: GPL
Keywords: Packet,socket,Handler,PacketHandler,Packet Handler,send,recv,serialize,serialization,deserialize,deserialization,compress,encrypt
License-File: LICENSE.txt
